omero/plugins/web.py
omeroweb/__init__.py
omeroweb/connector.py
omeroweb/custom_context_processor.py
omeroweb/custom_forms.py
omeroweb/decorators.py
omeroweb/filesessionstore.py
omeroweb/httprsp.py
omeroweb/manage.py
omeroweb/settings.py
omeroweb/urls.py
omeroweb/utils.py
omeroweb/version.py
omeroweb/wsgi.py
omeroweb/api/__init__.py
omeroweb/api/api_exceptions.py
omeroweb/api/api_marshal.py
omeroweb/api/api_query.py
omeroweb/api/api_settings.py
omeroweb/api/decorators.py
omeroweb/api/urls.py
omeroweb/api/views.py
omeroweb/feedback/__init__.py
omeroweb/feedback/forms.py
omeroweb/feedback/sendfeedback.py
omeroweb/feedback/urls.py
omeroweb/feedback/views.py
omeroweb/feedback/static/feedback/css/layout.css
omeroweb/feedback/static/feedback/image/bio-formats.svg
omeroweb/feedback/static/feedback/image/ome_logo.svg
omeroweb/feedback/static/feedback/image/omero.svg
omeroweb/feedback/templates/404.html
omeroweb/feedback/templates/500-nosubmit.html
omeroweb/feedback/templates/500.html
omeroweb/feedback/templates/base_error.html
omeroweb/feedback/templates/comment.html
omeroweb/feedback/templates/disabled.html
omeroweb/feedback/templates/error.html
omeroweb/feedback/templates/thanks.html
omeroweb/feedback/templatetags/__init__.py
omeroweb/feedback/templatetags/feedback_tags.py
omeroweb/license/agpl-3.0.txt
omeroweb/templates/nginx-development.conf.template
omeroweb/templates/nginx-location.conf.template
omeroweb/templates/nginx.conf.template
omeroweb/testlib/__init__.py
omeroweb/webadmin/__init__.py
omeroweb/webadmin/custom_forms.py
omeroweb/webadmin/forms.py
omeroweb/webadmin/models.py
omeroweb/webadmin/urls.py
omeroweb/webadmin/views.py
omeroweb/webadmin/webadmin_utils.py
omeroweb/webadmin/static/webadmin/css/chosen.css
omeroweb/webadmin/static/webadmin/css/drivespace.css
omeroweb/webadmin/static/webadmin/css/dusty.css
omeroweb/webadmin/static/webadmin/css/picklist.css
omeroweb/webadmin/static/webadmin/image/active.png
omeroweb/webadmin/static/webadmin/image/add.png
omero_web-5.30.1.dist-info/METADATA
omero_web-5.30.1.dist-info/WHEEL
omero_web-5.30.1.dist-info/top_level.txt
omero_web-5.30.1.dist-info/RECORD
