Metadata-Version: 2.4
Name: omero-web
Version: 5.30.1
Summary: OMERO.web
Home-page: https://github.com/ome/omero-web/
Author: The Open Microscopy Team
Author-email: ome-devel@lists.openmicroscopy.org.uk
License: GPLv2+
Classifier: Development Status :: 5 - Production/Stable
Classifier: Intended Audience :: Developers
Classifier: Intended Audience :: Science/Research
Classifier: Intended Audience :: System Administrators
Classifier: License :: OSI Approved :: GNU General Public License v2 or later (GPLv2+)
Classifier: Natural Language :: English
Classifier: Operating System :: OS Independent
Classifier: Programming Language :: Python :: 3
Classifier: Topic :: Software Development :: Libraries :: Python Modules
Requires-Python: >=3.10,<3.13
Requires-Dist: omero-py>=5.19.0
Requires-Dist: concurrent-log-handler>=0.9.20
Requires-Dist: Django<5.3,>=4.2.25
Requires-Dist: django-pipeline
Requires-Dist: django-cors-headers==3.7.0
Requires-Dist: whitenoise>=5.3.0
Requires-Dist: gunicorn>=19.3
Requires-Dist: omero-marshal>=0.7.0
Requires-Dist: Pillow
Requires-Dist: pytz
Requires-Dist: portalocker
Requires-Dist: packaging
Requires-Dist: importlib-resources
Provides-Extra: redis
Requires-Dist: django-redis==5.3.0; extra == "redis"
Dynamic: author
Dynamic: author-email
Dynamic: classifier
Dynamic: description
Dynamic: home-page
Dynamic: license
Dynamic: provides-extra
Dynamic: requires-dist
Dynamic: requires-python
Dynamic: summary
